s3_storage_provider.py
synapse_s3_storage_provider_delete_local-1.2.1.data/scripts/s3_media_upload
synapse_s3_storage_provider_delete_local-1.2.1.dist-info/LICENSE
synapse_s3_storage_provider_delete_local-1.2.1.dist-info/METADATA
synapse_s3_storage_provider_delete_local-1.2.1.dist-info/WHEEL
synapse_s3_storage_provider_delete_local-1.2.1.dist-info/top_level.txt
synapse_s3_storage_provider_delete_local-1.2.1.dist-info/RECORD
