Metadata-Version: 2.1
Name: synapse-s3-storage-provider-delete-local
Version: 1.2.1
Summary: A storage provider which can fetch and store media in Amazon S3 with local delete after upload
Home-page: https://github.com/matrix-org/synapse-s3-storage-provider
Author: daniel mazurkin
Classifier: Programming Language :: Python :: 3
Classifier: License :: OSI Approved :: Apache Software License
License-File: LICENSE
Requires-Dist: boto3 <2.0,>=1.9.23
Requires-Dist: botocore <2.0,>=1.12.23
Requires-Dist: humanize <0.6,>=0.5.1
Requires-Dist: psycopg2 <3.0,>=2.7.5
Requires-Dist: PyYAML <7.0,>=5.4
Requires-Dist: tqdm <5.0,>=4.26.0
Requires-Dist: Twisted
